peony/__init__.py
peony/blueprint.py
peony/peony.py
peony/master/__init__.py
peony/master/master.py
peony/master/task_queue_manager.py
peony/proxy/__init__.py
peony/proxy/proxy.py
peony/proxy/stat_counter.py
peony/proxy/connection/__init__.py
peony/proxy/connection/admin_connection.py
peony/proxy/connection/client_tcp_connection.py
peony/proxy/connection/client_udp_connection.py
peony/share/__init__.py
peony/share/config.py
peony/share/constants.py
peony/share/log.py
peony/share/mixins.py
peony/share/utils.py
peony/worker/__init__.py
peony/worker/request.py
peony/worker/worker.py
peony-1.0.35.data/scripts/peonyctl
peony-1.0.35.dist-info/METADATA
peony-1.0.35.dist-info/WHEEL
peony-1.0.35.dist-info/top_level.txt
peony-1.0.35.dist-info/RECORD
