Metadata-Version: 2.1
Name: peony
Version: 1.0.35
Home-page: https://github.com/dantezhu/peony
Author: dantezhu
Author-email: dantezhu <zny2008@gmail.com>
License: MIT
Project-URL: Homepage, https://github.com/dantezhu/peony
Platform: any
Requires-Python: >=3
Requires-Dist: maple (>=4.0.0)
Requires-Dist: setproctitle
Requires-Dist: twisted
Requires-Dist: events
Requires-Dist: netkit
Requires-Dist: click
Requires-Dist: pyglet
